clickclick/__init__.py
clickclick/console.py
clickclick-20.10.1.dist-info/LICENSE
clickclick-20.10.1.dist-info/METADATA
clickclick-20.10.1.dist-info/WHEEL
clickclick-20.10.1.dist-info/entry_points.txt
clickclick-20.10.1.dist-info/top_level.txt
clickclick-20.10.1.dist-info/RECORD
